zfit2/__init__.py
zfit2/_version.py
zfit2/_version.pyi
zfit2/py.typed
zfit2-0.0.1.dist-info/METADATA
zfit2-0.0.1.dist-info/WHEEL
zfit2-0.0.1.dist-info/licenses/LICENSE
zfit2-0.0.1.dist-info/RECORD
